LICENSE
MANIFEST.in
README.rst
VERSION
requirements.txt
setup.py
gym_2048/__init__.py
gym_2048/env.py
gym_2048.egg-info/PKG-INFO
gym_2048.egg-info/SOURCES.txt
gym_2048.egg-info/dependency_links.txt
gym_2048.egg-info/requires.txt
gym_2048.egg-info/top_level.txt