Metadata-Version: 2.1
Name: gym-2048
Version: 0.2.5
Summary: OpenAI Gym Environment for 2048
Home-page: https://www.github.com/activatedgeek/gym-2048
Author: Sanyam Kapoor
License: MIT
Platform: UNKNOWN
